[{"tm_no": "TM00", "name": "Mega Punch", "type": "0", "category": NaN, "PP": "20", "damage": "80", "accuracy": "85", "description": "The target is slugged by a punch thrown with muscle-packed power.", "_location": "Hammerlocke"}, {"tm_no": "TM01", "name": "Mega Kick", "type": "0", "category": NaN, "PP": "5", "damage": "120", "accuracy": "75", "description": "The target is attacked by a kick launched with muscle-packed power.", "_location": "Hammerlocke"}, {"tm_no": "TM02", "name": "Pay Day", "type": "0", "category": NaN, "PP": "20", "damage": "40", "accuracy": "100", "description": "Numerous coins are hurled at the target to inflict damage. Money is earned after the battle.", "_location": "Motostoke"}, {"tm_no": "TM03", "name": "Fire Punch", "type": "10", "category": NaN, "PP": "15", "damage": "75", "accuracy": "100", "description": "The target is punched with a fiery fist. This may also leave the target with a burn.", "_location": "Wyndon"}, {"tm_no": "TM04", "name": "Ice Punch", "type": "14", "category": NaN, "PP": "15", "damage": "75", "accuracy": "100", "description": "The target is punched with an icy fist. This may also leave the target frozen.", "_location": "Wyndon"}, {"tm_no": "TM05", "name": "Thunder Punch", "type": "13", "category": NaN, "PP": "15", "damage": "75", "accuracy": "100", "description": "The target is punched with an electrified fist. This may also leave the target with paralysis.", "_location": "Wyndon"}, {"tm_no": "TM06", "name": "Fly", "type": "2", "category": NaN, "PP": "15", "damage": "90", "accuracy": "95", "description": "The user flies up into the sky and then strikes its target on the next turn.", "_location": "Stow-on-Side"}, {"tm_no": "TM07", "name": "Pin Missile", "type": "6", "category": NaN, "PP": "20", "damage": "25", "accuracy": "95", "description": "Sharp spikes are shot at the target in rapid succession. They hit two to five times in a row.", "_location": "Route 4"}, {"tm_no": "TM08", "name": "Hyper Beam", "type": "0", "category": NaN, "PP": "5", "damage": "150", "accuracy": "90", "description": "The target is attacked with a powerful beam. The user can't move on the next turn.", "_location": "Wyndon"}, {"tm_no": "TM09", "name": "Giga Impact", "type": "0", "category": NaN, "PP": "5", "damage": "150", "accuracy": "90", "description": "The user charges at the target using every bit of its power. The user can't move on the next turn.", "_location": "Wyndon"}, {"tm_no": "TM10", "name": "Magical Leaf", "type": "12", "category": NaN, "PP": "20", "damage": "60", "accuracy": "101", "description": "The user scatters curious leaves that chase the target. This attack never misses.", "_location": "Turffield"}, {"tm_no": "TM11", "name": "Solar Beam", "type": "12", "category": NaN, "PP": "10", "damage": "120", "accuracy": "100", "description": "In this two-turn attack, the user gathers light, then blasts a bundled beam on the next turn.", "_location": "Turffield"}, {"tm_no": "TM12", "name": "Solar Blade", "type": "12", "category": NaN, "PP": "10", "damage": "125", "accuracy": "100", "description": "In this two-turn attack, the user gathers light and fills a blade with the light's energy, attacking the target on the next turn.", "_location": "Wyndon"}, {"tm_no": "TM13", "name": "Fire Spin", "type": "10", "category": NaN, "PP": "15", "damage": "35", "accuracy": "85", "description": "The target becomes trapped within a fierce vortex of fire that rages for four to five turns.", "_location": "Hammerlocke"}, {"tm_no": "TM14", "name": "Thunder Wave", "type": "13", "category": NaN, "PP": "20", "damage": "--", "accuracy": "90", "description": "The user launches a weak jolt of electricity that paralyzes the target.", "_location": "Wild Area"}, {"tm_no": "TM15", "name": "Dig", "type": "4", "category": NaN, "PP": "10", "damage": "80", "accuracy": "100", "description": "The user burrows into the ground, then attacks on the next turn.", "_location": "Route 6"}, {"tm_no": "TM16", "name": "Screech", "type": "0", "category": NaN, "PP": "40", "damage": "--", "accuracy": "85", "description": "An earsplitting screech harshly lowers the target's Defense stat.", "_location": "Circhester"}, {"tm_no": "TM17", "name": "Light Screen", "type": "8", "category": NaN, "PP": "30", "damage": "--", "accuracy": "101", "description": "A wondrous wall of light is put up to reduce damage from special attacks for five turns.", "_location": "Motostoke"}, {"tm_no": "TM18", "name": "Reflect", "type": "8", "category": NaN, "PP": "20", "damage": "--", "accuracy": "101", "description": "A wondrous wall of light is put up to reduce damage from physical attacks for five turns.", "_location": "Motostoke"}, {"tm_no": "TM19", "name": "Safeguard", "type": "0", "category": NaN, "PP": "25", "damage": "--", "accuracy": "101", "description": "The user creates a protective field that prevents status conditions for five turns.", "_location": "Motostoke"}, {"tm_no": "TM20", "name": "Self-Destruct", "type": "0", "category": NaN, "PP": "5", "damage": "200", "accuracy": "100", "description": "The user attacks everything around it by causing an explosion. The user faints upon using this move.", "_location": "Battle Tower"}, {"tm_no": "TM21", "name": "Rest", "type": "8", "category": NaN, "PP": "10", "damage": "--", "accuracy": "101", "description": "The user goes to sleep for two turns. This fully restores the user's HP and heals any status conditions.", "_location": "Ballonlea"}, {"tm_no": "TM22", "name": "Rock Slide", "type": "5", "category": NaN, "PP": "10", "damage": "75", "accuracy": "90", "description": "Large boulders are hurled at opposing Pok\u00e9mon to inflict damage. This may also make the opposing Pok\u00e9mon flinch.", "_location": "Route 9"}, {"tm_no": "TM23", "name": "Thief", "type": "16", "category": NaN, "PP": "25", "damage": "60", "accuracy": "100", "description": "The user attacks and steals the target's held item simultaneously. The user can't steal anything if it already holds an item.", "_location": "Hammerlocke"}, {"tm_no": "TM24", "name": "Snore", "type": "0", "category": NaN, "PP": "15", "damage": "50", "accuracy": "100", "description": "This attack can be used only if the user is asleep. The harsh noise may also make the target flinch.", "_location": "Glimwood Tangle"}, {"tm_no": "TM25", "name": "Protect", "type": "0", "category": NaN, "PP": "10", "damage": "--", "accuracy": "101", "description": "This move enables the user to protect itself from all attacks. Its chance of failing rises if it is used in succession.", "_location": "Motostoke"}, {"tm_no": "TM26", "name": "Scary Face", "type": "0", "category": NaN, "PP": "10", "damage": "--", "accuracy": "100", "description": "The user frightens the target with a scary face to harshly lower its Speed stat.", "_location": "Galar Mine"}, {"tm_no": "TM27", "name": "Icy Wind", "type": "14", "category": NaN, "PP": "15", "damage": "55", "accuracy": "95", "description": "The user attacks with a gust of chilled air. This also lowers opposing Pok\u00e9mon's Speed stats.", "_location": "Circhester"}, {"tm_no": "TM28", "name": "Giga Drain", "type": "12", "category": NaN, "PP": "10", "damage": "75", "accuracy": "100", "description": "A nutrient-draining attack. The user's HP is restored by half the damage taken by the target.", "_location": "Battle Tower"}, {"tm_no": "TM29", "name": "Charm", "type": "17", "category": NaN, "PP": "20", "damage": "--", "accuracy": "100", "description": "The user gazes at the target rather charmingly, making it less wary. This harshly lowers the target's Attack stat.", "_location": "Hammerlocke"}, {"tm_no": "TM30", "name": "Steel Wing", "type": "9", "category": NaN, "PP": "25", "damage": "70", "accuracy": "90", "description": "The target is hit with wings of steel. This may also raise the user's Defense stat.", "_location": "Route 6"}, {"tm_no": "TM31", "name": "Attract", "type": "0", "category": NaN, "PP": "15", "damage": "--", "accuracy": "100", "description": "If it is the opposite gender of the user, the target becomes infatuated and less likely to attack.", "_location": "Route 5"}, {"tm_no": "TM32", "name": "Sandstorm", "type": "5", "category": NaN, "PP": "10", "damage": "--", "accuracy": "101", "description": "A five-turn sandstorm is summoned to hurt all combatants except Rock, Ground, and Steel types. It raises the Sp. Def stat of Rock types.", "_location": "Hammerlocke"}, {"tm_no": "TM33", "name": "Rain Dance", "type": "11", "category": NaN, "PP": "5", "damage": "--", "accuracy": "101", "description": "The user summons a heavy rain that falls for five turns, powering up Water-type moves. It lowers the power of Fire-type moves.", "_location": "Hammerlocke"}, {"tm_no": "TM34", "name": "Sunny Day", "type": "10", "category": NaN, "PP": "5", "damage": "--", "accuracy": "101", "description": "The user intensifies the sun for five turns, powering up Fire-type moves. It lowers the power of Water-type moves.", "_location": "Hammerlocke"}, {"tm_no": "TM35", "name": "Hail", "type": "14", "category": NaN, "PP": "10", "damage": "--", "accuracy": "101", "description": "The user summons a hailstorm lasting five turns. It damages all Pok\u00e9mon except Ice types.", "_location": "Hammerlocke"}, {"tm_no": "TM36", "name": "Whirlpool", "type": "11", "category": NaN, "PP": "15", "damage": "35", "accuracy": "85", "description": "The user traps the target in a violent swirling whirlpool for four to five turns.", "_location": "Hulbury"}, {"tm_no": "TM37", "name": "Beat Up", "type": "16", "category": NaN, "PP": "10", "damage": "--", "accuracy": "100", "description": "The user gets all party Pok\u00e9mon to attack the target. The more party Pok\u00e9mon, the greater the number of attacks.", "_location": "Route 3"}, {"tm_no": "TM38", "name": "Will-O-Wisp", "type": "10", "category": NaN, "PP": "15", "damage": "--", "accuracy": "85", "description": "The user shoots a sinister flame at the target to inflict a burn.", "_location": "Motostoke"}, {"tm_no": "TM39", "name": "Facade", "type": "0", "category": NaN, "PP": "20", "damage": "70", "accuracy": "100", "description": "This attack move doubles its power if the user is poisoned, burned, or paralyzed.", "_location": "Motostoke Riverbank"}, {"tm_no": "TM40", "name": "Swift", "type": "0", "category": NaN, "PP": "20", "damage": "60", "accuracy": "101", "description": "Star-shaped rays are shot at opposing Pok\u00e9mon. This attack never misses.", "_location": "Wedgehurst"}, {"tm_no": "TM41", "name": "Helping Hand", "type": "0", "category": NaN, "PP": "20", "damage": "--", "accuracy": "101", "description": "The user assists an ally by boosting the power of that ally's attack.", "_location": "Motostoke"}, {"tm_no": "TM42", "name": "Revenge", "type": "1", "category": NaN, "PP": "10", "damage": "60", "accuracy": "100", "description": "This attack move's power is doubled if the user has been hurt by the opponent in the same turn.", "_location": "Stow-on-Side"}, {"tm_no": "TM43", "name": "Brick Break", "type": "1", "category": NaN, "PP": "15", "damage": "75", "accuracy": "100", "description": "The user attacks with a swift chop. It can also break barriers, such as Light Screen and Reflect.", "_location": "Route 8"}, {"tm_no": "TM44", "name": "Imprison", "type": "8", "category": NaN, "PP": "10", "damage": "--", "accuracy": "101", "description": "If opposing Pok\u00e9mon know any move also known by the user, they are prevented from using it.", "_location": "Battle Tower"}, {"tm_no": "TM45", "name": "Dive", "type": "11", "category": NaN, "PP": "10", "damage": "80", "accuracy": "100", "description": "Diving on the first turn, the user floats up and attacks on the next turn.", "_location": "Route 9"}, {"tm_no": "TM46", "name": "Weather Ball", "type": "0", "category": NaN, "PP": "10", "damage": "50", "accuracy": "100", "description": "This attack move varies in power and type depending on the weather.", "_location": "Hammerlocke"}, {"tm_no": "TM47", "name": "Fake Tears", "type": "16", "category": NaN, "PP": "20", "damage": "--", "accuracy": "100", "description": "The user feigns crying to fluster the target, harshly lowering its Sp. Def stat.", "_location": "Circhester"}, {"tm_no": "TM48", "name": "Rock Tomb", "type": "5", "category": NaN, "PP": "15", "damage": "60", "accuracy": "95", "description": "Boulders are hurled at the target. This also lowers the target's Speed stat by preventing its movement.", "_location": "Circhester"}, {"tm_no": "TM49", "name": "Sand Tomb", "type": "4", "category": NaN, "PP": "15", "damage": "35", "accuracy": "85", "description": "The user traps the target inside a harshly raging sandstorm for four to five turns.", "_location": "Galar Mine No. 2"}, {"tm_no": "TM50", "name": "Bullet Seed", "type": "12", "category": NaN, "PP": "30", "damage": "25", "accuracy": "100", "description": "The user forcefully shoots seeds at the target two to five times in a row.", "_location": "Hammerlocke"}, {"tm_no": "TM51", "name": "Icicle Spear", "type": "14", "category": NaN, "PP": "30", "damage": "25", "accuracy": "100", "description": "The user launches sharp icicles at the target two to five times in a row.", "_location": "Circhester"}, {"tm_no": "TM52", "name": "Bounce", "type": "2", "category": NaN, "PP": "5", "damage": "85", "accuracy": "85", "description": "The user bounces up high, then drops on the target on the second turn. This may also leave the target with paralysis.", "_location": "Battle Tower"}, {"tm_no": "TM53", "name": "Mud Shot", "type": "4", "category": NaN, "PP": "15", "damage": "55", "accuracy": "95", "description": "The user attacks by hurling a blob of mud at the target. This also lowers the target's Speed stat.", "_location": "Galar Mine No. 2"}, {"tm_no": "TM54", "name": "Rock Blast", "type": "5", "category": NaN, "PP": "10", "damage": "25", "accuracy": "90", "description": "The user hurls hard rocks at the target. Two to five rocks are launched in a row.", "_location": "Route 3"}, {"tm_no": "TM55", "name": "Brine", "type": "11", "category": NaN, "PP": "10", "damage": "65", "accuracy": "100", "description": "If the target's HP is half or less, this attack will hit with double the power.", "_location": "Hammerlocke"}, {"tm_no": "TM56", "name": "U-turn", "type": "6", "category": NaN, "PP": "20", "damage": "70", "accuracy": "100", "description": "After making its attack, the user rushes back to switch places with a party Pok\u00e9mon in waiting.", "_location": "Glimwood Tangle"}, {"tm_no": "TM57", "name": "Payback", "type": "16", "category": NaN, "PP": "10", "damage": "50", "accuracy": "100", "description": "The user stores power, then attacks. If the user moves after the target, this attack's power will be doubled.", "_location": "Route 2"}, {"tm_no": "TM58", "name": "Assurance", "type": "16", "category": NaN, "PP": "10", "damage": "60", "accuracy": "100", "description": "If the target has already taken some damage in the same turn, this attack's power is doubled.", "_location": "Route 7"}, {"tm_no": "TM59", "name": "Fling", "type": "16", "category": NaN, "PP": "10", "damage": "--", "accuracy": "100", "description": "The user flings its held item at the target to attack. This move's power and effects depend on the item.", "_location": "Battle Tower"}, {"tm_no": "TM60", "name": "Power Swap", "type": "8", "category": NaN, "PP": "10", "damage": "--", "accuracy": "101", "description": "The user employs its psychic power to switch changes to its Attack and Sp. Atk stats with the target.", "_location": "Wyndon"}, {"tm_no": "TM61", "name": "Guard Swap", "type": "8", "category": NaN, "PP": "10", "damage": "--", "accuracy": "101", "description": "The user employs its psychic power to switch changes to its Defense and Sp. Def stats with the target.", "_location": "Wyndon"}, {"tm_no": "TM62", "name": "Speed Swap", "type": "8", "category": NaN, "PP": "10", "damage": "--", "accuracy": "101", "description": "The user exchanges Speed stats with the target.", "_location": "Wyndon"}, {"tm_no": "TM63", "name": "Drain Punch", "type": "1", "category": NaN, "PP": "10", "damage": "75", "accuracy": "100", "description": "An energy-draining punch. The user's HP is restored by half the damage taken by the target.", "_location": "Wyndon"}, {"tm_no": "TM64", "name": "Avalanche", "type": "14", "category": NaN, "PP": "10", "damage": "60", "accuracy": "100", "description": "The power of this attack move is doubled if the user has been hurt by the target in the same turn.", "_location": "Route 9"}, {"tm_no": "TM65", "name": "Shadow Claw", "type": "7", "category": NaN, "PP": "15", "damage": "70", "accuracy": "100", "description": "The user slashes with a sharp claw made from shadows. Critical hits land more easily.", "_location": "Lake of Outrage"}, {"tm_no": "TM66", "name": "Thunder Fang", "type": "13", "category": NaN, "PP": "15", "damage": "65", "accuracy": "95", "description": "The user bites with electrified fangs. This may also make the target flinch or leave it with paralysis.", "_location": "Hammerlocke"}, {"tm_no": "TM67", "name": "Ice Fang", "type": "14", "category": NaN, "PP": "15", "damage": "65", "accuracy": "95", "description": "The user bites with cold-infused fangs. This may also make the target flinch or leave it frozen.", "_location": "Hammerlocke"}, {"tm_no": "TM68", "name": "Fire Fang", "type": "10", "category": NaN, "PP": "15", "damage": "65", "accuracy": "95", "description": "The user bites with flame-cloaked fangs. This may also make the target flinch or leave it with a burn.", "_location": "Hammerlocke"}, {"tm_no": "TM69", "name": "Psycho Cut", "type": "8", "category": NaN, "PP": "20", "damage": "70", "accuracy": "100", "description": "The user tears at the target with blades formed by psychic power. Critical hits land more easily.", "_location": "Route 2"}, {"tm_no": "TM70", "name": "Trick Room", "type": "8", "category": NaN, "PP": "5", "damage": "--", "accuracy": "101", "description": "The user creates a bizarre area in which slower Pok\u00e9mon get to move first for five turns.", "_location": "Battle Tower"}, {"tm_no": "TM71", "name": "Wonder Room", "type": "8", "category": NaN, "PP": "10", "damage": "--", "accuracy": "101", "description": "The user creates a bizarre area in which Pok\u00e9mon's Defense and Sp. Def stats are swapped for five turns.", "_location": "Battle Tower"}, {"tm_no": "TM72", "name": "Magic Room", "type": "8", "category": NaN, "PP": "10", "damage": "--", "accuracy": "101", "description": "The user creates a bizarre area in which Pok\u00e9mon's held items lose their effects for five turns.", "_location": "Battle Tower"}, {"tm_no": "TM73", "name": "Cross Poison", "type": "3", "category": NaN, "PP": "20", "damage": "70", "accuracy": "100", "description": "A slashing attack with a poisonous blade that may also poison the target. Critical hits land more easily.", "_location": "Dusty Bowl"}, {"tm_no": "TM74", "name": "Venoshock", "type": "3", "category": NaN, "PP": "10", "damage": "65", "accuracy": "100", "description": "The user drenches the target in a special poisonous liquid. This move's power is doubled if the target is poisoned.", "_location": "Stow-on-Side"}, {"tm_no": "TM75", "name": "Low Sweep", "type": "1", "category": NaN, "PP": "20", "damage": "65", "accuracy": "100", "description": "The user makes a swift attack on the target's legs, which lowers the target's Speed stat.", "_location": "Bridge Field"}, {"tm_no": "TM76", "name": "Round", "type": "0", "category": NaN, "PP": "15", "damage": "60", "accuracy": "100", "description": "The user attacks the target with a song. Others can join in the Round to increase the power of the attack.", "_location": "Motostoke"}, {"tm_no": "TM77", "name": "Hex", "type": "7", "category": NaN, "PP": "10", "damage": "65", "accuracy": "100", "description": "This relentless attack does massive damage to a target affected by status conditions.", "_location": "Ballonlea"}, {"tm_no": "TM78", "name": "Acrobatics", "type": "2", "category": NaN, "PP": "15", "damage": "55", "accuracy": "100", "description": "The user nimbly strikes the target. If the user is not holding an item, this attack inflicts massive damage.", "_location": "Ballonlea"}, {"tm_no": "TM79", "name": "Retaliate", "type": "0", "category": NaN, "PP": "5", "damage": "70", "accuracy": "100", "description": "The user gets revenge for a fainted ally. If an ally fainted in the previous turn, this move's power is increased.", "_location": "Hulbury"}, {"tm_no": "TM80", "name": "Volt Switch", "type": "13", "category": NaN, "PP": "20", "damage": "70", "accuracy": "100", "description": "After making its attack, the user rushes back to switch places with a party Pok\u00e9mon in waiting.", "_location": "Wild Area"}, {"tm_no": "TM81", "name": "Bulldoze", "type": "4", "category": NaN, "PP": "20", "damage": "60", "accuracy": "100", "description": "The user strikes everything around it by stomping down on the ground. This lowers the Speed stats of those hit.", "_location": "Giant's Seat"}, {"tm_no": "TM82", "name": "Electroweb", "type": "13", "category": NaN, "PP": "15", "damage": "55", "accuracy": "95", "description": "The user attacks and captures opposing Pok\u00e9mon using an electric net. This lowers their Speed stats.", "_location": "Hulbury"}, {"tm_no": "TM83", "name": "Razor Shell", "type": "11", "category": NaN, "PP": "10", "damage": "75", "accuracy": "95", "description": "The user cuts its target with sharp shells. This may also lower the target's Defense stat.", "_location": "Battle Tower"}, {"tm_no": "TM84", "name": "Tail Slap", "type": "0", "category": NaN, "PP": "10", "damage": "25", "accuracy": "85", "description": "The user attacks by striking the target with its hard tail. It hits the target two to five times in a row.", "_location": "Rolling Fields"}, {"tm_no": "TM85", "name": "Snarl", "type": "16", "category": NaN, "PP": "15", "damage": "55", "accuracy": "95", "description": "The user yells as if it's ranting about something, which lowers the Sp. Atk stats of opposing Pok\u00e9mon.", "_location": "Spikemuth"}, {"tm_no": "TM86", "name": "Phantom Force", "type": "7", "category": NaN, "PP": "10", "damage": "90", "accuracy": "100", "description": "The user vanishes somewhere, then strikes the target on the next turn. This move hits even if the target protects itself.", "_location": "Slumbering Weald"}, {"tm_no": "TM87", "name": "Draining Kiss", "type": "17", "category": NaN, "PP": "10", "damage": "50", "accuracy": "100", "description": "The user steals the target's HP with a kiss. The user's HP is restored by over half of the damage taken by the target.", "_location": "Ballonlea"}, {"tm_no": "TM88", "name": "Grassy Terrain", "type": "12", "category": NaN, "PP": "10", "damage": "--", "accuracy": "101", "description": "The user turns the ground to grass for five turns. This restores the HP of Pok\u00e9mon on the ground a little every turn and powers up Grass-type moves.", "_location": "Hammerlocke"}, {"tm_no": "TM89", "name": "Misty Terrain", "type": "17", "category": NaN, "PP": "10", "damage": "--", "accuracy": "101", "description": "This protects Pok\u00e9mon on the ground from status conditions and halves damage from Dragon-type moves for five turns.", "_location": "Hammerlocke"}, {"tm_no": "TM90", "name": "Electric Terrain", "type": "13", "category": NaN, "PP": "10", "damage": "--", "accuracy": "101", "description": "The user electrifies the ground for five turns, powering up Electric-type moves. Pok\u00e9mon on the ground no longer fall asleep.", "_location": "Hammerlocke"}, {"tm_no": "TM91", "name": "Psychic Terrain", "type": "8", "category": NaN, "PP": "10", "damage": "--", "accuracy": "101", "description": "This protects Pok\u00e9mon on the ground from priority moves and powers up Psychic-type moves for five turns.", "_location": "Hammerlocke"}, {"tm_no": "TM92", "name": "Mystical Fire", "type": "10", "category": NaN, "PP": "10", "damage": "75", "accuracy": "100", "description": "The user attacks by breathing a special, hot fire. This also lowers the target's Sp. Atk stat.", "_location": "Battle Tower"}, {"tm_no": "TM93", "name": "Eerie Impulse", "type": "13", "category": NaN, "PP": "15", "damage": "--", "accuracy": "100", "description": "The user's body generates an eerie impulse. Exposing the target to it harshly lowers the target's Sp. Atk stat.", "_location": "Wyndon"}, {"tm_no": "TM94", "name": "False Swipe", "type": "0", "category": NaN, "PP": "40", "damage": "40", "accuracy": "100", "description": "A restrained attack that prevents the target from fainting. The target is left with at least 1 HP.", "_location": "Motostoke"}, {"tm_no": "TM95", "name": "Air Slash", "type": "2", "category": NaN, "PP": "15", "damage": "75", "accuracy": "95", "description": "The user attacks with a blade of air that slices even the sky. This may also make the target flinch.", "_location": "Axew's Eye"}, {"tm_no": "TM96", "name": "Smart Strike", "type": "9", "category": NaN, "PP": "10", "damage": "70", "accuracy": "101", "description": "The user stabs the target with a sharp horn. This attack never misses.", "_location": "Route 8"}, {"tm_no": "TM97", "name": "Brutal Swing", "type": "16", "category": NaN, "PP": "20", "damage": "60", "accuracy": "100", "description": "The user swings its body around violently to inflict damage on everything in its vicinity.", "_location": "Turffield"}, {"tm_no": "TM98", "name": "Stomping Tantrum", "type": "4", "category": NaN, "PP": "10", "damage": "75", "accuracy": "100", "description": "Driven by frustration, the user attacks the target. If the user's previous move has failed, the power of this move doubles.", "_location": "Route 10"}, {"tm_no": "TM99", "name": "Breaking Swipe", "type": "15", "category": NaN, "PP": "15", "damage": "60", "accuracy": "100", "description": "The user swings its tough tail wildly and attacks opposing Pok\u00e9mon. This also lowers their Attack stats.", "_location": "Hammerlocke"}]